dcc_ex_py/AccessoryDecoders.py
dcc_ex_py/CVProgrammer.py
dcc_ex_py/DCCEX.py
dcc_ex_py/DigitalOutputs.py
dcc_ex_py/Helpers.py
dcc_ex_py/Memory.py
dcc_ex_py/Sensors.py
dcc_ex_py/TrackPower.py
dcc_ex_py/TrainEngines.py
dcc_ex_py/Turnouts.py
dcc_ex_py/__init__.py
dcc_ex_py/asyncsensor/AsyncSensor.py
dcc_ex_py/asyncsensor/__init__.py
dcc_ex_py-1.0.0.dist-info/licenses/LICENSE
dcc_ex_py-1.0.0.dist-info/METADATA
dcc_ex_py-1.0.0.dist-info/WHEEL
dcc_ex_py-1.0.0.dist-info/top_level.txt
dcc_ex_py-1.0.0.dist-info/RECORD
