Metadata-Version: 2.4
Name: DCC-EX_py
Version: 1.0.0
Summary: A simple way to connect to your DCC-EX controlled model railroad using python code without having to write DCC-EX commands into code. 
Author-email: Kaiden Richardson <kaidencr@gmail.com>
License: MIT
Project-URL: Documentation, https://github.com/Zenith08/DCC-EX_py/wiki
Project-URL: Repository, https://github.com/Zenith08/DCC-EX_py
Keywords: DCC-EX_py
Classifier: Intended Audience :: Developers
Classifier: License :: OSI Approved :: MIT License
Classifier: Natural Language :: English
Classifier: Programming Language :: Python :: 3.11
Classifier: Programming Language :: Python :: 3.12
Classifier: Programming Language :: Python :: 3.13
Requires-Python: >=3.11
License-File: LICENSE
Dynamic: license-file
